pygbag_network_utils/__init__.py
pygbag_network_utils/client/__init__.py
pygbag_network_utils/client/gui/__init__.py
pygbag_network_utils/client/gui/browser_console_handler.py
pygbag_network_utils/client/gui/button.py
pygbag_network_utils/client/gui/consts.py
pygbag_network_utils/client/gui/input_box.py
pygbag_network_utils/client/gui/list_view.py
pygbag_network_utils/client/socket/__init__.py
pygbag_network_utils/client/socket/websocket.py
pygbag_network_utils/server/__init__.py
pygbag_network_utils/server/game_server.py
pygbag_network_utils/server/master_server.py
pygbag_network_utils-0.1.2.dist-info/LICENSE
pygbag_network_utils-0.1.2.dist-info/METADATA
pygbag_network_utils-0.1.2.dist-info/WHEEL
pygbag_network_utils-0.1.2.dist-info/top_level.txt
pygbag_network_utils-0.1.2.dist-info/RECORD
