Metadata-Version: 2.2
Name: pygbag_network_utils
Version: 0.1.2
Summary: A Python library that provides network utilities for use with pygbag.
Author-email: thetechnicker <106349149+thetechnicker@users.noreply.github.com>
License: MIT License
Project-URL: Homepage, https://github.com/thetechnicker/pygbag_network_utils
Classifier: Programming Language :: Python :: 3
Classifier: License :: OSI Approved :: MIT License
Classifier: Operating System :: OS Independent
Requires-Python: >=3.6
License-File: LICENSE
